[
  {
    "_id": {
      "$oid": "6203d3ea7a012673527c8d23"
    },
    "projectId": "abc",
    "data": {
      "status": {
        "gantt": false,
        "details": true,
        "team": false,
        "costs": false,
        "revenue": false,
        "setup": false,
        "risks": false
      },
      "details": {
        "productPlatformName": "My First Project on the server",
        "applicationNumber": "123445",
        "nature": "Process",
        "ipProtection": "protection",
        "projectName": "first Project",
        "projectLength": 3,
        "startMonth": "Jan",
        "startYear": 2021,
        "projectManager": "projectManager",
        "software": "software",
        "matchFunding": "funding",
        "ganttRef": "ganttRef",
        "riskRef": "riskRef",
        "competitor": "competitor"
      },
      "lead": {
        "companyName": "lead company",
        "companyAcronym": "acronym",
        "organisationType": "type",
        "organisationSize": "size",
        "postcode": "postcode",
        "turnover": 20000,
        "lastFinancialMonth": "",
        "lastFinancialYear": "year",
        "lawyer": "lawyer",
        "bankHolidays": 3,
        "annualLeave": 27,
        "numEmployees": 10,
        "overheadRate": 10,
        "partnerFunding": "",
        "fundingLevel": 10,
        "matchFundingSource": "source",
        "investorName": "name",

        "detailsComplete": false,
        "teamComplete": false,
        "ganttComplete": false,
        "costsComplete": false,
        "revenueComplete": false,
        "risksComplete": false
      },
      "pOne": {
        "companyName": "Company One",
        "companyAcronym": "",
        "organisationType": "",
        "organisationSize": "",
        "postcode": "",
        "turnover": 0,
        "lastFinancialMonth": "",
        "lastFinancialYear": "",
        "lawyer": "",
        "bankHolidays": 0,
        "annualLeave": 0,
        "numEmployees": 0,
        "overheadRate": 10,
        "partnerFunding": 0,
        "fundingLevel": 0,
        "matchFundingSource": "",
        "investorName": "",

        "detailsComplete": false,
        "teamComplete": false,
        "ganttComplete": false,
        "costsComplete": false,
        "revenueComplete": false,
        "risksComplete": false
      },
      "pTwo": {
        "companyName": "edit the company name...",
        "companyAcronym": "acronym",
        "organisationType": "type",
        "organisationSize": "size",
        "postcode": "postcode",
        "turnover": 20000,
        "lastFinancialMonth": "",
        "lastFinancialYear": "year",
        "lawyer": "lawyer",
        "bankHolidays": 3,
        "annualLeave": 30,
        "numEmployees": 10,
        "overheadRate": 10,
        "partnerFunding": "partner",
        "fundingLevel": 10,
        "matchFundingSource": "source",
        "investorName": "name",

        "detailsComplete": false,
        "teamComplete": false,
        "ganttComplete": false,
        "costsComplete": false,
        "revenueComplete": false,
        "risksComplete": false
      },
      "wizard": {
        "currentQuestionIndex": 0,
        "allQuestionsAsked": false,
        "complete": false,
        "component": "questions",
        "progress": "0%",
        "answers": {}
      },
      "settings": {
        "resourcesIncrement": 5
      },
      "templates": [
        {
          "riskId": "man1",
          "riskType": "managerial",
          "riskCategory": "gen",
          "riskDescription": "Project documentation/evidence is inadequate resulting in project delays",
          "riskPreProbability": 2,
          "riskPreConsequence": 2,
          "riskMitigation": "Continuous assessment and action plan for the documentation/evidence gathered during project to avoid delays",
          "riskPostProbability": 2,
          "riskPostConsequence": 2
        },
        {
          "riskId": "man2",
          "riskType": "managerial",
          "riskCategory": "gen",
          "riskDescription": "Resources required to meet technical needs exceed expectation",
          "riskPreProbability": 2,
          "riskPreConsequence": 2,
          "riskMitigation": "Project Manager will continually assess tasks and resources. Continuous effort on recruitment using existing networks will prevent delays in project delivery",
          "riskPostProbability": 2,
          "riskPostConsequence": 2
        },
        {
          "riskId": "man3",
          "riskType": "managerial",
          "riskCategory": "gen",
          "riskDescription": "Misinterpretation leads to technical errors",
          "riskPreProbability": 2,
          "riskPreConsequence": 2,
          "riskMitigation": "Agile development means that issues will be found quickly and rectified. Monthly project progress meetings and online space for documents will ensure technical information is clear/accessible",
          "riskPostProbability": 2,
          "riskPostConsequence": 2
        },
        {
          "riskId": "man4",
          "riskType": "managerial",
          "riskCategory": "gen",
          "riskDescription": "Key team member incapacitated",
          "riskPreProbability": 2,
          "riskPreConsequence": 2,
          "riskMitigation": "Standards and progress reports will ensure smooth handover. Regular team feedback ensures PM understands progress. Learning points are captured in a team wiki, which allows for fast knowledge transfer",
          "riskPostProbability": 2,
          "riskPostConsequence": 2
        },
        {
          "riskId": "man5",
          "riskType": "managerial",
          "riskCategory": "gen",
          "riskDescription": "Insufficient resourcing of the new members of the team compromises the ability to deliver project",
          "riskPreProbability": 2,
          "riskPreConsequence": 2,
          "riskMitigation": "All key members of the team already sourced. Team members are committed to the project through supportive company culture and robust project/performance management structures",
          "riskPostProbability": 2,
          "riskPostConsequence": 2
        },
        {
          "riskId": "man6",
          "riskType": "managerial",
          "riskCategory": "gen",
          "riskDescription": "Changing requirements or scope creep delay development",
          "riskPreProbability": 2,
          "riskPreConsequence": 2,
          "riskMitigation": "Agile methodologies and milestones to fence requirements. Management will encourage an open and transparent development environment that helps identify delays",
          "riskPostProbability": 2,
          "riskPostConsequence": 2
        },
        {
          "riskId": "man7",
          "riskType": "managerial",
          "riskCategory": "gen",
          "riskDescription": "Key team member incapacitated",
          "riskPreProbability": 2,
          "riskPreConsequence": 2,
          "riskMitigation": "Standards and progress reports will ensure smooth handover. Regular team feedback ensures PM understands progress. Learning points are captured in a team wiki, which allows for fast knowledge transfer",
          "riskPostProbability": 2,
          "riskPostConsequence": 2
        },
        {
          "riskId": "man8",
          "riskType": "managerial",
          "riskCategory": "gen",
          "riskDescription": "Unable to recruit to fill team gaps from known contacts",
          "riskPreProbability": 2,
          "riskPreConsequence": 2,
          "riskMitigation": "Team has extensive experienced in recruitment. Initial, confidential discussions with several potential candidates, who have expressed interest but cannot confirm until project finance is secured. Project has been planned with roles involving these people",
          "riskPostProbability": 2,
          "riskPostConsequence": 2
        },
        {
          "riskId": "man9",
          "riskType": "managerial",
          "riskCategory": "gen",
          "riskDescription": "Development team are too distracted with project and development of core business is neglected",
          "riskPreProbability": 2,
          "riskPreConsequence": 2,
          "riskMitigation": "Monthly board meetings to ensure strategy delivers business plan. Independent chairman and investor director",
          "riskPostProbability": 2,
          "riskPostConsequence": 2
        }
      ],
      "roles": [],
      "tasks": [
        {
          "taskTitle": "Account Compliance (KYC, AML)",
          "category": "fin",
          "taskType": "Finance Sector",
          "taskId": "1"
        },
        {
          "taskTitle": "Agile Sprint Planning",
          "category": "gen",
          "taskType": "Project Management",
          "taskId": "2"
        },

        {
          "taskTitle": "AI/ML Training ",
          "category": "ai",
          "taskType": "Artificial Intelligence",
          "taskId": "3"
        },
        {
          "taskTitle": "Algorithm Development and Refinement",
          "category": "gen",
          "taskType": "General",
          "taskId": "4"
        }
      ]
    }
  }
]
