[{
  "_id": {
    "$oid": "6203d3ea7a012673527c8d23"
  },
  "projectId": "abc",
  "data": [
    {
      "riskId": "1030d587-94e4-47a8-97bd-c2a2ed668d2a",
      "riskType": "managerial",
      "riskDescription": "Description...",
      "riskMitigation": "Mitigation...",
      "riskPreProbability": 3,
      "riskPreConsequence": 2,
      "riskPostProbability": 1,
      "riskPostConsequence": 2,
      "category": null,
      "height": 72,
      "riskValue": 6
    },
    {
      "riskId": "77eabdf7-8d44-4098-923d-1a01ecfa1981",
      "riskType": "managerial",
      "riskDescription": "Stuff doesn't work the way that it should",
      "riskMitigation": "Something good can be done to mitigate",
      "riskPreProbability": 3,
      "riskPreConsequence": 2,
      "riskPostProbability": 1,
      "riskPostConsequence": 2,
      "category": null,
      "height": 72,
      "riskOwner": "JD",
      "riskValue": 2
    },
    {
      "riskId": "fae60d55-7be3-4209-af2b-2d19c8bec907",
      "riskType": "managerial",
      "riskDescription": "Platform not scalable enough to support business plan",
      "riskMitigation": "Something to make it scalable",
      "riskPreProbability": 2,
      "riskPreConsequence": 1,
      "riskPostProbability": 2,
      "riskPostConsequence": 1,
      "category": null,
      "height": 72,
      "riskValue": 2,
      "riskOwner": "FH"
    }
  ]
}]